dataset_creator/__init__.py
dataset_creator/bankit.py
dataset_creator/base_dataset.py
dataset_creator/creator.py
dataset_creator/dataset.py
dataset_creator/enums.py
dataset_creator/exceptions.py
dataset_creator/genbank_fasta.py
dataset_creator/mega.py
dataset_creator/phylip.py
dataset_creator/tnt.py
dataset_creator/utils.py
dataset_creator-0.7.0.dist-info/licenses/AUTHORS.rst
dataset_creator-0.7.0.dist-info/licenses/LICENSE
dataset_creator-0.7.0.dist-info/METADATA
dataset_creator-0.7.0.dist-info/WHEEL
dataset_creator-0.7.0.dist-info/entry_points.txt
dataset_creator-0.7.0.dist-info/top_level.txt
dataset_creator-0.7.0.dist-info/RECORD
