Metadata-Version: 2.4
Name: dataset-creator
Version: 0.7.0
Summary: Takes SeqRecordExpanded objects and creates datasets for phylogenetic software
Home-page: https://github.com/carlosp420/dataset-creator
Author: Carlos Peña
Author-email: mycalesis@gmail.com
License: BSD-3-clause
Classifier: Development Status :: 2 - Pre-Alpha
Classifier: Intended Audience :: Developers
Classifier: Operating System :: Unix
Classifier: Operating System :: POSIX
Classifier: Programming Language :: Python
Classifier: Programming Language :: Python :: 3
Classifier: Programming Language :: Python :: 3.10
Classifier: Programming Language :: Python :: 3.11
Classifier: Programming Language :: Python :: 3.12
Classifier: Topic :: Utilities
License-File: LICENSE
License-File: AUTHORS.rst
Requires-Dist: degenerate-dna==0.1.2
Requires-Dist: seqrecord-expanded==0.2.16
Dynamic: author
Dynamic: author-email
Dynamic: classifier
Dynamic: description
Dynamic: home-page
Dynamic: license
Dynamic: license-file
Dynamic: requires-dist
Dynamic: summary
